{
  "updated": "2026-06-10",
  "source": "https://www.notbeinggreen.com/feed",
  "posts": [
    {
      "title": "Politics have made the future more uncertain than ever for young scientists",
      "link": "https://www.notbeinggreen.com/p/politics-have-made-the-future-more",
      "pubDate": "Tue, 26 May 2026 21:52:30 GMT",
      "description": "The NIH funds programs meant to support promising young researchers. For some reason, they have halted."
    },
    {
      "title": "Shocker, if people think they are treated unfairly, it might be bad for their health",
      "link": "https://www.notbeinggreen.com/p/shocker-if-people-think-they-are",
      "pubDate": "Fri, 01 May 2026 12:20:46 GMT",
      "description": "What my first published dissertation paper says about healthcare discrimination and heart disease"
    },
    {
      "title": "The Privilege to Wait",
      "link": "https://www.notbeinggreen.com/p/the-privilege-to-wait",
      "pubDate": "Wed, 01 Apr 2026 12:27:16 GMT",
      "description": "Academic research has always been a game of delayed gratification. When the system falls, waiting becomes a privilege."
    },
    {
      "title": "The Future of Science Is Built on Trust and Transparency",
      "link": "https://www.notbeinggreen.com/p/the-future-of-science-is-built-on",
      "pubDate": "Tue, 03 Mar 2026 13:09:59 GMT",
      "description": "I asked NIH Director Jay Bhattacharya to be more transparent about what makes a grant a \"DEI activity.\" Instead of answering, he decided to criticize my science without reading it."
    },
    {
      "title": "The Promise and Reality of Investing in Early Career Scientists",
      "link": "https://www.notbeinggreen.com/p/the-promise-and-reality-of-investing",
      "pubDate": "Tue, 17 Feb 2026 12:37:39 GMT",
      "description": "An overview of historical data from the F99/K00 award at the National Institute of Health, from an awardee"
    }
  ]
}
